{
  "CommonHeader": {
    "description": "Auto imported from components/CommonHeader.vue"
  },
  "CommonSidebar": {
    "description": "Auto imported from components/CommonSidebar.vue"
  },
  "Error": {
    "description": "Auto imported from components/Error.vue"
  },
  "Home": {
    "description": "Auto imported from components/Home.vue"
  },
  "Login": {
    "description": "Auto imported from components/Login.vue"
  },
  "NuxtLogo": {
    "description": "Auto imported from components/NuxtLogo.vue"
  },
  "Tutorial": {
    "description": "Auto imported from components/Tutorial.vue"
  },
  "Loader": {
    "description": "Auto imported from components/loader.vue"
  },
  "AdminToHeader": {
    "description": "Auto imported from components/Admin/Admin_ToHeader.vue"
  },
  "AdminAdminsidebar": {
    "description": "Auto imported from components/Admin/Adminsidebar.vue"
  },
  "AdminModule1": {
    "description": "Auto imported from components/Admin/Module1.vue"
  },
  "AdminModule2": {
    "description": "Auto imported from components/Admin/Module2.vue"
  },
  "AdminRolesaccess": {
    "description": "Auto imported from components/Admin/rolesaccess.vue"
  },
  "AdminRolesmatrix": {
    "description": "Auto imported from components/Admin/rolesmatrix.vue"
  },
  "AdminScreenmanagement": {
    "description": "Auto imported from components/Admin/screenmanagement.vue"
  },
  "AdminScreenpage": {
    "description": "Auto imported from components/Admin/screenpage.vue"
  }
}
